odoo/addons/base_unece/README.rst
odoo/addons/base_unece/__init__.py
odoo/addons/base_unece/__manifest__.py
odoo/addons/base_unece/i18n/base_unece.pot
odoo/addons/base_unece/i18n/nl.po
odoo/addons/base_unece/models/__init__.py
odoo/addons/base_unece/models/unece_code_list.py
odoo/addons/base_unece/readme/CONFIGURE.rst
odoo/addons/base_unece/readme/CONTRIBUTORS.rst
odoo/addons/base_unece/readme/DESCRIPTION.rst
odoo/addons/base_unece/security/ir.model.access.csv
odoo/addons/base_unece/static/description/icon.png
odoo/addons/base_unece/static/description/index.html
odoo/addons/base_unece/views/unece_code_list.xml
odoo13_addon_base_unece-13.0.1.1.1.dist-info/METADATA
odoo13_addon_base_unece-13.0.1.1.1.dist-info/WHEEL
odoo13_addon_base_unece-13.0.1.1.1.dist-info/top_level.txt
odoo13_addon_base_unece-13.0.1.1.1.dist-info/RECORD
